steel_toes/__init__.py
steel_toes/cli.py
steel_toes/core.py
steel_toes/hook.py
steel_toes/steel_toes.py
steel_toes-0.5.0.dist-info/METADATA
steel_toes-0.5.0.dist-info/WHEEL
steel_toes-0.5.0.dist-info/entry_points.txt
steel_toes-0.5.0.dist-info/licenses/LICENSE
steel_toes-0.5.0.dist-info/RECORD
