Metadata-Version: 2.1
Name: steel-toes
Version: 0.5.0
Summary: protection against stepping on teammates toes in a kedro project
Project-URL: homepage, https://github.com/WaylonWalker/steel-toes
Project-URL: issues, https://github.com/WaylonWalker/steel-toes/issues
Project-URL: docs, https://steel-toes.kedro.dev/
Author-email: Waylon Walker <waylon@waylonwalker.com>
License-Expression: MIT
License-File: LICENSE
Classifier: Development Status :: 4 - Beta
Classifier: Environment :: Console
Classifier: Intended Audience :: Developers
Classifier: License :: OSI Approved :: MIT License
Classifier: Natural Language :: English
Classifier: Operating System :: OS Independent
Classifier: Programming Language :: Python :: 3.7
Classifier: Programming Language :: Python :: 3.8
Classifier: Programming Language :: Python :: 3.9
Classifier: Programming Language :: Python :: 3.10
Classifier: Programming Language :: Python :: 3.11
Requires-Dist: click
Requires-Dist: colorama
Requires-Dist: kedro
